Metadata-Version: 2.1
Name: ddgcli
Version: 0.2.1
Summary: A ddg unnoficcial cli
Home-page: https://github.com/borisd93/ddgcli
Author: x93bd
Author-email: edkz@nogafam.me
License: GPL 3
Keywords: duckduckgo,cli
Platform: UNKNOWN
Classifier: Development Status :: 3 - Alpha
License-File: LICENSE
